fsm/__init__.py
fsm/exceptions.py
fsm/fsm.py
fsmpy-2.1.0.dist-info/LICENSE
fsmpy-2.1.0.dist-info/WHEEL
fsmpy-2.1.0.dist-info/METADATA
fsmpy-2.1.0.dist-info/RECORD
