Metadata-Version: 2.1
Name: fsmpy
Version: 2.1.0
Summary: Minimal state machine
Home-page: https://github.com/Woile/pyfsm
License: MIT
Keywords: finite,state,machine,minimal
Author: Santiago Fraire Willemoes
Author-email: santiwilly@gmail.com
Classifier: Development Status :: 5 - Production/Stable
Classifier: Intended Audience :: Developers
Classifier: License :: OSI Approved :: MIT License
Classifier: Programming Language :: Python :: 2
Classifier: Programming Language :: Python :: 2.7
Classifier: Programming Language :: Python :: 3
Classifier: Programming Language :: Python :: 3.4
Classifier: Programming Language :: Python :: 3.5
Classifier: Programming Language :: Python :: 3.6
Classifier: Programming Language :: Python :: 3.7
Classifier: Programming Language :: Python :: 3.8
Classifier: Programming Language :: Python :: 3.9
Project-URL: Documentation, https://pyfsm.readthedocs.io/en/latest/
Project-URL: Repository, https://github.com/Woile/pyfsm
